[
    {
        "question": "How does quantum computing (QC) fit alongside classical computing?",
        "type": "many_choice",
        "answers": [
            { "answer": "QC can be better than classical computing for specific problems", "correct": true, "feedback": "Correct." },
            { "answer": "QC can replace classical high-performance computing", "correct": false, "feedback": "Incorrect." },
            { "answer": "QC can replace accelerators like GPU and FPGA", "correct": false, "feedback": "Incorrect." },
            { "answer": "QC can efficiently process big volumes of data", "correct": false, "feedback": "Incorrect." }
        ]
    },
    {
        "question": "What types of problems is quantum computing (QC) likely to be good at?",
        "type": "many_choice",
        "answers": [
            { "answer": "Efficiently simulate complex systems based on quantum mechanics", "correct": true, "feedback": "Correct." },
            { "answer": "Improve accuracy/efficiency of optimisation and search problems", "correct": true, "feedback": "Correct." },
            { "answer": "Optimise/accelerate certain parts of AI model training", "correct": true, "feedback": "Correct." },
            { "answer": "Train AI models end-to-end", "correct": false, "feedback": "Incorrect." },
            { "answer": "Render 3D models in complex simulations", "correct": false, "feedback": "Incorrect." },
            { "answer": "Process data in real-time for high-throughput computing", "correct": false, "feedback": "Incorrect." }
        ]
    },
    {
        "question": "What does NISQ stand for?",
        "type": "many_choice",
        "answers": [
            { "answer": "Noisy Intermediate-Scale Quantum", "correct": true, "feedback": "Correct." },
            { "answer": "Noisy Interim-Sized Quantum", "correct": false, "feedback": "Incorrect." },
            { "answer": "Noisy Interim-Scale Quantum", "correct": false, "feedback": "Incorrect." },
            { "answer": "Narrow Intermediate-Scale Quantum", "correct": false, "feedback": "Incorrect." }
        ]
    },
    {
        "question": "Which of the following are limitations of NISQ systems for practical applications?",
        "type": "many_choice",
        "answers": [
            { "answer": "Noise & fidelity", "correct": true, "feedback": "Correct." },
            { "answer": "Errors & decoherence", "correct": true, "feedback": "Correct." },
            { "answer": "Storage space", "correct": false, "feedback": "Incorrect." },
            { "answer": "Power consumption", "correct": false, "feedback": "Incorrect." }
        ]
    },
    {
        "question": "What is decoherence in NISQ systems?",
        "type": "many_choice",
        "answers": [
            { "answer": "Uncontrolled change of quantum states causing information loss", "correct": true, "feedback": "Correct." },
            { "answer": "Inability of quantum gates to communicate with each other", "correct": false, "feedback": "Incorrect." },
            { "answer": "Inefficient connectivity between qubits in the NISQ system", "correct": false, "feedback": "Incorrect." },
            { "answer": "Percentage of error-free operations in qubits", "correct": false, "feedback": "Incorrect." }
        ]
    },
    {
        "question": "What type of skills are required for developing quantum computing applications?",
        "type": "many_choice",
        "answers": [
            { "answer": "Quantum information, algorithmics, programming & domain expertise", "correct": true, "feedback": "Correct." },
            { "answer": "Quantum physics, mechanics & engineering", "correct": false, "feedback": "Incomplete." },
            { "answer": "Algorithms & domain expertise", "correct": false, "feedback": "Incomplete." },
            { "answer": "Data science, AI & programming", "correct": false, "feedback": "Incomplete." }
        ]
    },
    {
        "question": "How is quantum computing currently being exploited?",
        "type": "many_choice",
        "answers": [
            { "answer": "Organisations that use classical computing are co-developing and/or investigating quantum computing", "correct": true, "feedback": "Correct." },
            { "answer": "Quantum computing is useful only for scientists & researchers", "correct": false, "feedback": "Incorrect." },
            { "answer": "Quantum computing is not yet useful to any organisation", "correct": false, "feedback": "Incorrect." },
            { "answer": "Many sectors & organisations are developing operational/production applications", "correct": false, "feedback": "Incorrect." }
        ]
    },
    {
        "question": "Which of the following are sister technologies of quantum computing?",
        "type": "many_choice",
        "answers": [
            { "answer": "Quantum cloning", "correct": false, "feedback": "Incorrect." },
            { "answer": "Quantum simulation", "correct": true, "feedback": "Correct." },
            { "answer": "Quantum communication", "correct": true, "feedback": "Correct." },
            { "answer": "Quantum sensing/metrology", "correct": true, "feedback": "Correct." }
        ]
    }
]